avdb/__init__.py
avdb/__main__.py
avdb/__version__.py
avdb/csdb.py
avdb/model.py
avdb/subcmd.py
avdb/templates.py
avdb-1.3.0.dist-info/LICENSE.txt
avdb-1.3.0.dist-info/METADATA
avdb-1.3.0.dist-info/WHEEL
avdb-1.3.0.dist-info/entry_points.txt
avdb-1.3.0.dist-info/top_level.txt
avdb-1.3.0.dist-info/RECORD
