Metadata-Version: 2.1
Name: avdb
Version: 1.3.0
Summary: AFS version tracking database
Home-page: https://github.com/meffie/avdb
Author: Michael Meffie
Author-email: mmeffie@sinenomine.net
License: UNKNOWN
Platform: UNKNOWN
Classifier: Development Status :: 4 - Beta
Classifier: Environment :: Console
Classifier: Intended Audience :: Developers
Classifier: License :: OSI Approved :: BSD License
Classifier: Operating System :: POSIX
Classifier: Programming Language :: Python :: 2.7
Classifier: Programming Language :: Python :: 3
Classifier: Topic :: Software Development
Requires-Dist: SQLAlchemy
Requires-Dist: dnspython
Requires-Dist: mpipe
Requires-Dist: pystache
Requires-Dist: sh
Requires-Dist: six
